airo_dataset_tools/__init__.py
airo_dataset_tools/cli.py
airo_dataset_tools/py.typed
airo_dataset_tools/segmentation_mask_converter.py
airo_dataset_tools/coco_tools/__init__.py
airo_dataset_tools/coco_tools/change_coco_images_prefix.py
airo_dataset_tools/coco_tools/coco_instances_to_yolo.py
airo_dataset_tools/coco_tools/fiftyone_viewer.py
airo_dataset_tools/coco_tools/merge_datasets.py
airo_dataset_tools/coco_tools/split_dataset.py
airo_dataset_tools/coco_tools/transform_dataset.py
airo_dataset_tools/coco_tools/transforms.py
airo_dataset_tools/cvat_labeling/__init__.py
airo_dataset_tools/cvat_labeling/convert_cvat_to_coco.py
airo_dataset_tools/cvat_labeling/load_xml_to_dict.py
airo_dataset_tools/data_parsers/__init__.py
airo_dataset_tools/data_parsers/camera_intrinsics.py
airo_dataset_tools/data_parsers/coco.py
airo_dataset_tools/data_parsers/cvat_images.py
airo_dataset_tools/data_parsers/pose.py
airo_dataset_tools-2026.1.0.dist-info/METADATA
airo_dataset_tools-2026.1.0.dist-info/WHEEL
airo_dataset_tools-2026.1.0.dist-info/entry_points.txt
airo_dataset_tools-2026.1.0.dist-info/top_level.txt
airo_dataset_tools-2026.1.0.dist-info/RECORD
