Metadata-Version: 2.4
Name: airo-dataset-tools
Version: 2026.1.0
Summary: Scripts for loading and converting datasets for the Ghent University AI and Robotics Lab
Author: Victor-Louis De Gusseme
Author-email: victorlouisdg@gmail.com
Requires-Dist: numpy>=2.0
Requires-Dist: pydantic>2.0.0
Requires-Dist: opencv-contrib-python==4.10.0.84
Requires-Dist: opencv-python-headless==4.10.0.84
Requires-Dist: pycocotools
Requires-Dist: xmltodict
Requires-Dist: tqdm
Requires-Dist: fiftyone
Requires-Dist: Pillow
Requires-Dist: types-Pillow
Requires-Dist: albumentations
Requires-Dist: click
Requires-Dist: airo-typing>=2026.1.0
Requires-Dist: airo-spatial-algebra>=2026.1.0
Dynamic: author
Dynamic: author-email
Dynamic: requires-dist
Dynamic: summary
